django_airflow/__init__.py
django_airflow-0.0.1.dist-info/METADATA
django_airflow-0.0.1.dist-info/WHEEL
django_airflow-0.0.1.dist-info/LICENSE
django_airflow-0.0.1.dist-info/RECORD
